discordpy_slash/__init__.py
discordpy_slash/slash.py
discordpy_slash-11.0.0.dist-info/LICENSE
discordpy_slash-11.0.0.dist-info/METADATA
discordpy_slash-11.0.0.dist-info/WHEEL
discordpy_slash-11.0.0.dist-info/top_level.txt
discordpy_slash-11.0.0.dist-info/RECORD
