Metadata-Version: 2.1
Name: discordpy_slash
Version: 11.0.0
Summary: A package that you can use to easily implement slash commands and buttons into your Discord bot
Home-page: https://github.com/TricolorHen061/discordpy-slash
Author: TricolorHen061
Author-email: thisemaildoesntexistsopleasedontemailit@ndlsa.djsadlk
License: UNKNOWN
Project-URL: Bug Tracker, https://github.com/TricolorHen061/discordpy-slash/issues
Platform: UNKNOWN
Classifier: Programming Language :: Python :: 3
Classifier: License :: OSI Approved :: MIT License
Classifier: Operating System :: OS Independent
Requires-Python: >=3.6
License-File: LICENSE
